{
  "annonument": [
    {
      "title": "test version quention",
      "in_link": "/hw/hw-test",
      "out_link": "",
      "description": "測試題目，有空的可以測試看看有沒有問題",
      "time": "2025-02-20"
    }
  ],
  "test": "yanami anna",
  "student": [
    {
      "id": "archie0732",
      "intro": "",
      "neme": "archie",
      "avatar": "https://i.pinimg.com/550x/76/54/ef/7654efd01209b2189806bc6cc81ed2c3.jpg",
      "hw": [
        "1",
        "",
        "",
        "",
        "",
        "",
        "",
        "",
        "",
        "",
        ""
      ],
      "name": "archie0732"
    }
  ]
}